llama_index/embeddings/nebius/__init__.py
llama_index/embeddings/nebius/base.py
llama_index/embeddings/nebius/utils.py
llama_index_embeddings_nebius-0.4.1.dist-info/METADATA
llama_index_embeddings_nebius-0.4.1.dist-info/WHEEL
llama_index_embeddings_nebius-0.4.1.dist-info/licenses/LICENSE
llama_index_embeddings_nebius-0.4.1.dist-info/RECORD
